<?xml version="1.0" encoding="UTF-8"?>
<objects serializationModel="Studio.02.02.00">
	<object class="Event" id="{dbc5219e-54a5-4aa4-a384-9df66f81339a}">
		<property name="name">
			<value>Room 2</value>
		</property>
		<property name="outputFormat">
			<value>1</value>
		</property>
		<relationship name="folder">
			<destination>{c4c3d876-09c7-44e9-9c46-6e1dda2e751d}</destination>
		</relationship>
		<relationship name="mixer">
			<destination>{fa48d343-6ce0-441c-a67b-3b00be5871a3}</destination>
		</relationship>
		<relationship name="masterTrack">
			<destination>{6672d7b5-e875-4e6f-b760-744e26b32bd0}</destination>
		</relationship>
		<relationship name="mixerInput">
			<destination>{188541c2-3823-4a4c-94b7-cbc6fb3aec36}</destination>
		</relationship>
		<relationship name="automatableProperties">
			<destination>{8dc40c82-193c-4b85-b51e-ef94fb36d4f7}</destination>
		</relationship>
		<relationship name="markerTracks">
			<destination>{07952bfc-ebe0-4bd8-8cfa-8b276839bb2c}</destination>
		</relationship>
		<relationship name="groupTracks">
			<destination>{2ec7c303-e296-47f0-b951-ca336cbfaa81}</destination>
		</relationship>
		<relationship name="timeline">
			<destination>{a5e2fc66-eab1-4ffa-af39-9cb3bb3ab693}</destination>
		</relationship>
		<relationship name="banks">
			<destination>{3c5b4e2d-49b1-4a25-a08a-df46dfecf1ae}</destination>
		</relationship>
	</object>
	<object class="EventMixer" id="{fa48d343-6ce0-441c-a67b-3b00be5871a3}">
		<relationship name="masterBus">
			<destination>{80ff9360-0b4d-4600-89e3-fca632a2485d}</destination>
		</relationship>
	</object>
	<object class="MasterTrack" id="{6672d7b5-e875-4e6f-b760-744e26b32bd0}">
		<relationship name="mixerGroup">
			<destination>{80ff9360-0b4d-4600-89e3-fca632a2485d}</destination>
		</relationship>
	</object>
	<object class="MixerInput" id="{188541c2-3823-4a4c-94b7-cbc6fb3aec36}">
		<relationship name="effectChain">
			<destination>{3e695c2a-9fe7-4e02-b3ad-bdfdbc1ccf1b}</destination>
		</relationship>
		<relationship name="panner">
			<destination>{b47419f6-3e8d-4e95-8a76-44afa0bdffec}</destination>
		</relationship>
		<relationship name="output">
			<destination>{9a01186a-7712-40a4-be41-d0ba3754454f}</destination>
		</relationship>
	</object>
	<object class="EventAutomatableProperties" id="{8dc40c82-193c-4b85-b51e-ef94fb36d4f7}" />
	<object class="MarkerTrack" id="{07952bfc-ebe0-4bd8-8cfa-8b276839bb2c}" />
	<object class="GroupTrack" id="{2ec7c303-e296-47f0-b951-ca336cbfaa81}">
		<relationship name="modules">
			<destination>{902158a8-834e-4abb-a793-f363d7f7d7cc}</destination>
		</relationship>
		<relationship name="mixerGroup">
			<destination>{17722fbd-822d-4a1c-b838-3d107b11ffe1}</destination>
		</relationship>
	</object>
	<object class="Timeline" id="{a5e2fc66-eab1-4ffa-af39-9cb3bb3ab693}">
		<relationship name="modules">
			<destination>{902158a8-834e-4abb-a793-f363d7f7d7cc}</destination>
		</relationship>
		<relationship name="markers">
			<destination>{8f2328b3-b19d-459f-bb01-0f62570d1032}</destination>
		</relationship>
	</object>
	<object class="EventMixerMaster" id="{80ff9360-0b4d-4600-89e3-fca632a2485d}">
		<relationship name="modulators">
			<destination>{f687afae-420a-4e6c-8cbf-982f44f96ba9}</destination>
		</relationship>
		<relationship name="effectChain">
			<destination>{7969553d-a6c8-4814-a55e-fb9bfdb7c810}</destination>
		</relationship>
		<relationship name="panner">
			<destination>{bd5c3225-67cb-48b4-98ea-bcf31820c5fa}</destination>
		</relationship>
		<relationship name="mixer">
			<destination>{fa48d343-6ce0-441c-a67b-3b00be5871a3}</destination>
		</relationship>
	</object>
	<object class="MixerBusEffectChain" id="{3e695c2a-9fe7-4e02-b3ad-bdfdbc1ccf1b}">
		<relationship name="effects">
			<destination>{bc3de2ab-a0db-4d25-b20e-25a0f5c291a3}</destination>
		</relationship>
	</object>
	<object class="MixerBusPanner" id="{b47419f6-3e8d-4e95-8a76-44afa0bdffec}" />
	<object class="SingleSound" id="{902158a8-834e-4abb-a793-f363d7f7d7cc}">
		<property name="length">
			<value>131.68326530612245</value>
		</property>
		<relationship name="audioFile">
			<destination>{43b2cd99-0230-471e-8871-aa9660194858}</destination>
		</relationship>
	</object>
	<object class="EventMixerGroup" id="{17722fbd-822d-4a1c-b838-3d107b11ffe1}">
		<property name="name">
			<value>Audio 1</value>
		</property>
		<relationship name="modulators">
			<destination>{e3b8b55b-e880-4e3c-8ad0-52d2675697ef}</destination>
		</relationship>
		<relationship name="effectChain">
			<destination>{4fbdc7db-1b56-4fac-92e4-abd81eba8611}</destination>
		</relationship>
		<relationship name="panner">
			<destination>{f87fcc7f-1f5b-453d-b015-b3ebaa8aa428}</destination>
		</relationship>
		<relationship name="output">
			<destination>{80ff9360-0b4d-4600-89e3-fca632a2485d}</destination>
		</relationship>
	</object>
	<object class="LoopRegion" id="{8f2328b3-b19d-459f-bb01-0f62570d1032}">
		<property name="position">
			<value>0</value>
		</property>
		<property name="length">
			<value>131.68326530612245</value>
		</property>
		<relationship name="timeline">
			<destination>{a5e2fc66-eab1-4ffa-af39-9cb3bb3ab693}</destination>
		</relationship>
		<relationship name="markerTrack">
			<destination>{07952bfc-ebe0-4bd8-8cfa-8b276839bb2c}</destination>
		</relationship>
	</object>
	<object class="ADSRModulator" id="{f687afae-420a-4e6c-8cbf-982f44f96ba9}">
		<property name="nameOfPropertyBeingModulated">
			<value>volume</value>
		</property>
		<property name="initialValue">
			<value>-80</value>
		</property>
		<property name="finalValue">
			<value>-80</value>
		</property>
	</object>
	<object class="MixerBusEffectChain" id="{7969553d-a6c8-4814-a55e-fb9bfdb7c810}">
		<relationship name="effects">
			<destination>{8fd406ca-bf02-484f-8a15-647568aef642}</destination>
		</relationship>
	</object>
	<object class="MixerBusPanner" id="{bd5c3225-67cb-48b4-98ea-bcf31820c5fa}" />
	<object class="MixerBusFader" id="{bc3de2ab-a0db-4d25-b20e-25a0f5c291a3}" />
	<object class="ADSRModulator" id="{e3b8b55b-e880-4e3c-8ad0-52d2675697ef}">
		<property name="nameOfPropertyBeingModulated">
			<value>volume</value>
		</property>
		<property name="initialValue">
			<value>-80</value>
		</property>
		<property name="finalValue">
			<value>-80</value>
		</property>
	</object>
	<object class="MixerBusEffectChain" id="{4fbdc7db-1b56-4fac-92e4-abd81eba8611}">
		<relationship name="effects">
			<destination>{f155c8f1-df9d-4d6b-86ac-01598ca19058}</destination>
		</relationship>
	</object>
	<object class="MixerBusPanner" id="{f87fcc7f-1f5b-453d-b015-b3ebaa8aa428}" />
	<object class="MixerBusFader" id="{8fd406ca-bf02-484f-8a15-647568aef642}" />
	<object class="MixerBusFader" id="{f155c8f1-df9d-4d6b-86ac-01598ca19058}" />
</objects>
